webview_flask/__init__.py
webview_flask/main.py
webview_flask-0.1.1.dist-info/METADATA
webview_flask-0.1.1.dist-info/WHEEL
webview_flask-0.1.1.dist-info/entry_points.txt
webview_flask-0.1.1.dist-info/RECORD
