Metadata-Version: 2.1
Name: webview-flask
Version: 0.1.1
Summary: flask app with webview
Author: Sander van Dragt
Author-email: sander@vandragt.com
Requires-Python: >=3.8.0,<3.12
Classifier: Programming Language :: Python :: 3
Classifier: Programming Language :: Python :: 3.8
Classifier: Programming Language :: Python :: 3.9
Classifier: Programming Language :: Python :: 3.10
Classifier: Programming Language :: Python :: 3.11
Requires-Dist: Flask (>=2.3.2,<3.0.0)
Requires-Dist: pygobject (>=3.44.1,<4.0.0)
Requires-Dist: pywebview (>=4.1,<5.0)
